[
    {
        "dates": "February 2026 - Present",
        "description": "Software Engineer Apprentice at Flatiron School"
    },
    {
        "dates": "May 2022 - August 2022",
        "description": "Software Development Engineer Intern at Amazon"
    },
    {
        "dates": "July 2021 - December 2021, July 2022 - February 2023",
        "description": "Software Engineer Co-Op → Software Engineer at HubSpot"
    },
    {
        "dates": "March 2020 - July 2020",
        "description": "Engineer at RetireUp"
    }
]